Workbook
Name Slicer_Category: #N/A
Name Slicer_City: #N/A
Name Slicer_Month: #N/A
Name Slicer_Sales_Person: #N/A

Sheet Sales Data
A1: ORDER ID | B1: CUSTOMER | C1: CITY | D1: PRODUCT | E1: CATEGORY | F1: QUANTITY | G1: UNIT PRICE | H1: SALES | I1: high sales | M1: delhi sales
A2: 1001 | B2: ANU | C2: KOTA | D2: LAPTOP | E2: ELECTRONIC | F2: 2 | G2: 55000 | H2: 110000 | I2: =IF(H2>20000,"high","low") -> high | M2: =SUMIF(C2:C11,C10,H2:H11) -> 980
A3: 1007 | B3: RAVI | C3: MUMBAI | D3: LAPTOP | E3: ELECTRONIC | F3: 2 | G3: 55000 | H3: 110000 | I3: =IF(H3>20000,"high","low") -> high | M3: =COUNTIF(C2:C11,C10) -> 1
A4: 1009 | B4: YASHVI | C4: JAIPUR | D4: LAPTOP | E4: ELECTRONIC | F4: 2 | G4: 55000 | H4: 110000 | I4: =IF(H4>20000,"high","low") -> high | M4: jaipur
A5: 1004 | B5: CHIKU | C5: MUMBAI | D5: PHONE | E5: ELECTRONIC | F5: 6 | G5: 35000 | H5: 45000 | I5: =IF(H5>20000,"high","low") -> high | M5: =SUMIF(C2:C11,C6,H2:H11) -> 155800
A6: 1008 | B6: SAHIL | C6: JAIPUR | D6: PHONE | E6: ELECTRONIC | F6: 1 | G6: 35000 | H6: 45000 | I6: =IF(H6>20000,"high","low") -> high | M6: =COUNTIF(C2:C11,C6) -> 3
A7: 1003 | B7: BHUMI | C7: KOTA | D7: DESK | E7: FURNITURE | F7: 1 | G7: 5000 | H7: 7000 | I7: =IF(H7>20000,"high","low") -> low | M7: mumbai
A8: 1006 | B8: YASH | C8: KOTA | D8: CHAIR | E8: FURNITURE | F8: 4 | G8: 4000 | H8: 7000 | I8: =IF(H8>20000,"high","low") -> low | M8: =SUMIF(C2:C11,C5,H2:H11) -> 156000
A9: 1010 | B9: VISHNU | C9: MUMBAI | D9: HEADPHONE | E9: ELECTRONIC | F9: 4 | G9: 600 | H9: 1000 | I9: =IF(H9>20000,"high","low") -> low | M9: =COUNTIF(C2:C11,C5) -> 3
A10: 1002 | B10: AASHU | C10: DELHI | D10: KEYBOARD | E10: ACESSORIES | F10: 4 | G10: 700 | H10: 980 | I10: =IF(H10>20000,"high","low") -> low | M10: kota
A11: 1005 | B11: DEVESH | C11: JAIPUR | D11: PHONECOVER | E11: ACESSORIES | F11: 3 | G11: 500 | H11: 800 | I11: =IF(H11>20000,"high","low") -> low | M11: =SUMIF(C2:C11,C2,H2:H11) -> 124000
M12: =COUNTIF(C2:C11,C2) -> 3
A15: total sales | B15: average | C15: minimum | D15: maximum | E15: count
A16: =SUM(H2:H11) -> 436780 | B16: =AVERAGE(H2:H11) -> 43678 | C16: =MIN(H2:H11) -> 800 | D16: =MAX(H2:H11) -> 110000 | E16: =COUNT(H2:H11) -> 10
A19: EMPLOYEE ID | B19: NAME | C19: DEPARTMENT | D19: SALARY | E19: AGE | F19: EXPERIENCE | G19: RATING | H19: BONUS | I19: BONUS ELEGIBLE | J19: TOTAL SALARY
A20: 25021 | B20: aysha | C20: sales | D20: 30000 | E20: 21 | F20: 1yr | G20: 3.9 | H20: 3000 | I20: =IF(G20>3.7,"BONUS","NO BONUS") -> BONUS | J20: =SUM($D20,$H20) -> 33000
A21: 25022 | B21: bhumika | C21: analyst | D21: 34000 | E21: 25 | F21: 3yr | G21: 4 | H21: 5000 | I21: =IF(G21>3.7,"BONUS","NO BONUS") -> BONUS | J21: =SUM($D21,$H21) -> 39000
A22: 25023 | B22: charu | C22: cyber | D22: 32000 | E22: 23 | F22: 2yr | G22: 4 | H22: 4000 | I22: =IF(G22>3.7,"BONUS","NO BONUS") -> BONUS | J22: =SUM($D22,$H22) -> 36000
A23: 25024 | B23: gauri | C23: developer | D23: 40000 | E23: 26 | F23: 4yr | G23: 4.5 | H23: 6000 | I23: =IF(G23>3.7,"BONUS","NO BONUS") -> BONUS | J23: =SUM($D23,$H23) -> 46000
A24: 25025 | B24: khushi | C24: analyst | D24: 28000 | E24: 23 | F24: 2yr | G24: 4.2 | H24: 2500 | I24: =IF(G24>3.7,"BONUS","NO BONUS") -> BONUS | J24: =SUM($D24,$H24) -> 30500
A25: 25026 | B25: lavi | C25: sales | D25: 29000 | E25: 24 | F25: 3yr | G25: 3.7 | H25: 2000 | I25: =IF(G25>3.7,"BONUS","NO BONUS") -> NO BONUS | J25: =SUM($D25,$H25) -> 31000
A26: 25027 | B26: manvi | C26: developer | D26: 45000 | E26: 26 | F26: 4yr | G26: 4 | H26: 5000 | I26: =IF(G26>3.7,"BONUS","NO BONUS") -> BONUS | J26: =SUM($D26,$H26) -> 50000
A27: 25028 | B27: priya | C27: cyber | D27: 25000 | E27: 25 | F27: 2yr | G27: 3.5 | H27: 2000 | I27: =IF(G27>3.7,"BONUS","NO BONUS") -> NO BONUS | J27: =SUM($D27,$H27) -> 27000
A28: 25029 | B28: yashi | C28: analyst | D28: 35000 | E28: 21 | F28: 2yr | G28: 4.5 | H28: 5500 | I28: =IF(G28>3.7,"BONUS","NO BONUS") -> BONUS | J28: =SUM($D28,$H28) -> 40500
A29: 25030 | B29: vishi | C29: analyst | D29: 32000 | E29: 24 | F29: 3yr | G29: 4 | H29: 4500 | I29: =IF(G29>3.7,"BONUS","NO BONUS") -> BONUS | J29: =SUM($D29,$H29) -> 36500
A32: SALES | B32: CYBER | C32: DEVELOPER | D32: ANALYST
A33: =COUNTIF(C20:C29,C20) -> 2 | B33: =COUNTIF(C20:C29,C22) -> 2 | C33: =COUNTIF(C20:C29,C23) -> 2 | D33: =COUNTIF(C20:C29,C21) -> 4
A34: =SUMIF(C20:C29,C20,J20:J29) -> 64000 | B34: =SUMIF(C20:C29,C22,J20:J29) -> 63000 | C34: =SUMIF(C20:C29,C23,J20:J29) -> 96000 | D34: =SUMIF(C20:C29,C21,J20:J29) -> 146500
A35: =AVERAGEIF(C20:C29,C20,J20:J29) -> 32000 | B35: =AVERAGEIF(C20:C29,C22,J20:J29) -> 31500 | C35: =AVERAGEIF(C20:C29,C23,J20:J29) -> 48000 | D35: =AVERAGEIF(C20:C29,C21,J20:J29) -> 36625

Sheet product prices
A1: PRODUCT | B1: PRICE
A2: LAPTOP | B2: =VLOOKUP('Sales Data'!D2,CHOOSE({1,2},'Sales Data'!D2:D11,'Sales Data'!G2:G11),2,) -> 55000
A3: LAPTOP | B3: =VLOOKUP('Sales Data'!D3,CHOOSE({1,2},'Sales Data'!D3:D12,'Sales Data'!G3:G12),2,) -> 55000
A4: LAPTOP | B4: =VLOOKUP('Sales Data'!D4,CHOOSE({1,2},'Sales Data'!D4:D13,'Sales Data'!G4:G13),2,) -> 55000
A5: PHONE | B5: =VLOOKUP('Sales Data'!D5,CHOOSE({1,2},'Sales Data'!D5:D14,'Sales Data'!G5:G14),2,) -> 35000
A6: PHONE | B6: =VLOOKUP('Sales Data'!D6,CHOOSE({1,2},'Sales Data'!D6:D15,'Sales Data'!G6:G15),2,) -> 35000
A7: DESK | B7: =VLOOKUP('Sales Data'!D7,CHOOSE({1,2},'Sales Data'!D7:D16,'Sales Data'!G7:G16),2,) -> 5000
A8: CHAIR | B8: =VLOOKUP('Sales Data'!D8,CHOOSE({1,2},'Sales Data'!D8:D17,'Sales Data'!G8:G17),2,) -> 4000
A9: HEADPHONE | B9: =VLOOKUP('Sales Data'!D9,CHOOSE({1,2},'Sales Data'!D9:D18,'Sales Data'!G9:G18),2,) -> 600
A10: KEYBOARD | B10: =VLOOKUP('Sales Data'!D10,CHOOSE({1,2},'Sales Data'!D10:D19,'Sales Data'!G10:G19),2,) -> 700
A11: PHONECOVER | B11: =VLOOKUP('Sales Data'!D11,CHOOSE({1,2},'Sales Data'!D11:D20,'Sales Data'!G11:G20),2,) -> 500

Sheet sales data1
A1: Order ID | B1: Date | C1: Month | D1: Product | E1: Category | F1: City | G1: Sales Person | H1: Units Sold | I1: Price | J1: Sales | K1: Profit | M1: TOTAL SALES
A2: 1001 | B2: 46024 | C2: Jan | D2: Laptop | E2: Electronics | F2: Delhi | G2: Aman | H2: 2 | I2: 55000 | J2: 110000 | K2: 18000 | M2: =SUM(Table1[Sales]) -> 979600
A3: 1002 | B3: 46025 | C3: Jan | D3: Shoes | E3: Fashion | F3: Mumbai | G3: Riya | H3: 5 | I3: 2000 | J3: 10000 | K3: 3000 | M3: TOTAL PROFIT
A4: 1003 | B4: 46027 | C4: Jan | D4: Mobile | E4: Electronics | F4: Jaipur | G4: Arjun | H4: 4 | I4: 25000 | J4: 100000 | K4: 20000 | M4: =SUM(Table1[Profit]) -> 200600
A5: 1004 | B5: 46030 | C5: Jan | D5: Watch | E5: Accessories | F5: Delhi | G5: Karan | H5: 6 | I5: 3000 | J5: 18000 | K5: 4000 | M5: HIGHEST SALES
A6: 1005 | B6: 46034 | C6: Jan | D6: Headphones | E6: Electronics | F6: Pune | G6: Riya | H6: 8 | I6: 1500 | J6: 12000 | K6: 3500 | M6: =MAX(Table1[Sales]) -> 127500
A7: 1006 | B7: 46037 | C7: Jan | D7: Bag | E7: Fashion | F7: Jaipur | G7: Aman | H7: 7 | I7: 1200 | J7: 8400 | K7: 2500 | M7: LOWEST SALES
A8: 1007 | B8: 46042 | C8: Jan | D8: Tablet | E8: Electronics | F8: Mumbai | G8: Arjun | H8: 3 | I8: 30000 | J8: 90000 | K8: 17000 | M8: =MIN(Table1[Sales]) -> 8400
A9: 1008 | B9: 46047 | C9: Jan | D9: Shoes | E9: Fashion | F9: Delhi | G9: Karan | H9: 4 | I9: 2200 | J9: 8800 | K9: 2700 | M9: TOTAL UNITS SOLD
A10: 1009 | B10: 46055 | C10: Feb | D10: Laptop | E10: Electronics | F10: Pune | G10: Aman | H10: 1 | I10: 55000 | J10: 55000 | K10: 12000 | M10: =SUM(Table1[Units Sold]) -> 99
A11: 1010 | B11: 46058 | C11: Feb | D11: Mobile | E11: Electronics | F11: Delhi | G11: Riya | H11: 3 | I11: 26000 | J11: 78000 | K11: 16000 | M11: TOTAL SALES IN DELHI
A12: 1011 | B12: 46063 | C12: Feb | D12: Watch | E12: Accessories | F12: Mumbai | G12: Arjun | H12: 7 | I12: 3200 | J12: 22400 | K12: 5000 | M12: =SUMIF(Table1[City],F2,Table1[Sales]) -> 360300
A13: 1012 | B13: 46068 | C13: Feb | D13: Bag | E13: Fashion | F13: Jaipur | G13: Karan | H13: 6 | I13: 1400 | J13: 8400 | K13: 2200 | M13: TOTAL SALES OF ELECTRONICS
A14: 1013 | B14: 46073 | C14: Feb | D14: Headphones | E14: Electronics | F14: Delhi | G14: Aman | H14: 10 | I14: 1800 | J14: 18000 | K14: 5000 | M14: =SUMIF(Table1[Category],E2,Table1[Sales]) -> 861500
A15: 1014 | B15: 46078 | C15: Feb | D15: Tablet | E15: Electronics | F15: Pune | G15: Riya | H15: 2 | I15: 32000 | J15: 64000 | K15: 13000 | M15: TOTAL PROFIT OF FASHION
A16: 1015 | B16: 46084 | C16: Mar | D16: Shoes | E16: Fashion | F16: Mumbai | G16: Arjun | H16: 8 | I16: 2100 | J16: 16800 | K16: 4500 | M16: =SUMIF(Table1[Category],E3,Table1[Profit]) -> 17900
A17: 1016 | B17: 46089 | C17: Mar | D17: Laptop | E17: Electronics | F17: Jaipur | G17: Karan | H17: 2 | I17: 57000 | J17: 114000 | K17: 22000 | M17: PRODUCST SOLD IN JAIPURE
A18: 1017 | B18: 46093 | C18: Mar | D18: Mobile | E18: Electronics | F18: Delhi | G18: Riya | H18: 5 | I18: 25500 | J18: 127500 | K18: 26000 | M18: =COUNTIF(Table1[City],F4) -> 5
A19: 1018 | B19: 46099 | C19: Mar | D19: Bag | E19: Fashion | F19: Pune | G19: Aman | H19: 9 | I19: 1300 | J19: 11700 | K19: 3000 | M19: MAX. SALES PERSON
A20: 1019 | B20: 46103 | C20: Mar | D20: Tablet | E20: Electronics | F20: Mumbai | G20: Karan | H20: 3 | I20: 31000 | J20: 93000 | K20: 18000 | M20: RIYA
A21: 1020 | B21: 46109 | C21: Mar | D21: Watch | E21: Accessories | F21: Jaipur | G21: Arjun | H21: 4 | I21: 3400 | J21: 13600 | K21: 3200 | M21: LAPTOP SALES BY XLOOKUP
M22: =_xlfn.XLOOKUP(D2,Table1[Product],Table1[Sales]) -> 110000
M23: TOTAL FEB. PROFIT
M24: =SUMIF(Table1[Month],C10,Table1[Profit]) -> 53200
M25: TOTAL ORDERS
M26: =COUNT(Table1[Order ID]) -> 20

Sheet pivot tables
A3: Row Labels | B3: Sum of Sales | D3: Row Labels | E3: Sum of Profit | G3: Row Labels | H3: Sum of Sales | J3: Row Labels | K3: Sum of Sales
A4: Delhi | B4: 360300 | D4: Bag | E4: 7700 | G4: Jan | H4: 357200 | J4: Accessories | K4: 54000
A5: Jaipur | B5: 244400 | D5: Headphones | E5: 8500 | G5: Feb | H5: 245800 | J5: Electronics | K5: 861500
A6: Mumbai | B6: 232200 | D6: Laptop | E6: 52000 | G6: Mar | H6: 376600 | J6: Fashion | K6: 64100
A7: Pune | B7: 142700 | D7: Mobile | E7: 62000 | G7: Grand Total | H7: 979600 | J7: Grand Total | K7: 979600
A8: Grand Total | B8: 979600 | D8: Shoes | E8: 10200
D9: Tablet | E9: 48000
D10: Watch | E10: 12200
D11: Grand Total | E11: 200600
A14: Row Labels | B14: Sum of Units Sold | D14: Row Labels | E14: Sum of Sales | F14: Sum of Profit | G14: Sum of Units Sold
A15: Aman | B15: 29 | D15: Aman | E15: 203100 | F15: 40500 | G15: 29
A16: Arjun | B16: 26 | D16: Arjun | E16: 242800 | F16: 49700 | G16: 26
A17: Karan | B17: 21 | D17: Karan | E17: 242200 | F17: 48900 | G17: 21
A18: Riya | B18: 23 | D18: Riya | E18: 291500 | F18: 61500 | G18: 23
A19: Grand Total | B19: 99 | D19: Grand Total | E19: 979600 | F19: 200600 | G19: 99

Sheet DASHBOARD
A1: SALES DASHBOARD
